linsecure/__init__.py
linsecure/cli.py
linsecure/core.py
linsecure/checks/__init__.py
linsecure/checks/firewall.py
linsecure/checks/permissions.py
linsecure/checks/ports.py
linsecure/checks/ssh.py
linsecure/checks/system.py
linsecure/checks/updates.py
linsecure-0.1.3.dist-info/LICENSE
linsecure-0.1.3.dist-info/METADATA
linsecure-0.1.3.dist-info/WHEEL
linsecure-0.1.3.dist-info/top_level.txt
linsecure-0.1.3.dist-info/RECORD
