Metadata-Version: 2.1
Name: linsecure
Version: 0.1.3
Summary: A lightweight Linux vulnerability scanner
Author-email: Ashok Kumar <ashok.thaur8857@gmail.com>
Requires-Python: >=3.7
License-File: LICENSE
Provides-Extra: dev
Requires-Dist: pytest; extra == "dev"
